sifaka/__init__.py
sifaka/api.py
sifaka/py.typed
sifaka/core/__init__.py
sifaka/core/constants.py
sifaka/core/embeddings.py
sifaka/core/exceptions.py
sifaka/core/interfaces.py
sifaka/core/llm_client.py
sifaka/core/llm_client_pool.py
sifaka/core/metrics.py
sifaka/core/middleware.py
sifaka/core/models.py
sifaka/core/monitoring.py
sifaka/core/plugin_interfaces.py
sifaka/core/plugin_loader.py
sifaka/core/plugins.py
sifaka/core/protocols.py
sifaka/core/retry.py
sifaka/core/type_defs.py
sifaka/core/types.py
sifaka/core/validation.py
sifaka/core/config/__init__.py
sifaka/core/config/base.py
sifaka/core/config/composite.py
sifaka/core/config/critic.py
sifaka/core/config/engine.py
sifaka/core/config/llm.py
sifaka/core/config/storage.py
sifaka/core/config/validation.py
sifaka/core/engine/__init__.py
sifaka/core/engine/core.py
sifaka/core/engine/generation.py
sifaka/core/engine/orchestration.py
sifaka/core/engine/validation.py
sifaka/critics/__init__.py
sifaka/critics/agent4debate.py
sifaka/critics/constitutional.py
sifaka/critics/meta_rewarding.py
sifaka/critics/n_critics.py
sifaka/critics/prompt.py
sifaka/critics/reflexion.py
sifaka/critics/self_consistency.py
sifaka/critics/self_rag.py
sifaka/critics/self_refine.py
sifaka/critics/self_taught_evaluator.py
sifaka/critics/style.py
sifaka/critics/core/__init__.py
sifaka/critics/core/base.py
sifaka/critics/core/confidence.py
sifaka/critics/core/factory.py
sifaka/critics/core/registry.py
sifaka/storage/__init__.py
sifaka/storage/base.py
sifaka/storage/file.py
sifaka/storage/memory.py
sifaka/storage/multi.py
sifaka/storage/redis.py
sifaka/tools/__init__.py
sifaka/tools/arxiv.py
sifaka/tools/base.py
sifaka/tools/registry.py
sifaka/tools/types.py
sifaka/tools/web_search.py
sifaka/tools/wikipedia.py
sifaka/validators/__init__.py
sifaka/validators/base.py
sifaka/validators/basic.py
sifaka/validators/composable.py
sifaka/validators/guardrails.py
sifaka/validators/numeric.py
sifaka/validators/pattern.py
sifaka-0.2.0.dist-info/licenses/LICENSE
sifaka-0.2.0.dist-info/METADATA
sifaka-0.2.0.dist-info/WHEEL
sifaka-0.2.0.dist-info/top_level.txt
sifaka-0.2.0.dist-info/RECORD
