Metadata-Version: 2.4
Name: sifaka
Version: 0.2.0
Summary: Simple AI text improvement through research-backed critique with complete observability
Author-email: Evan Volgas <evan.volgas@gmail.com>
License-Expression: MIT
Keywords: ai,llm,validation,text-improvement,critique
Classifier: Development Status :: 4 - Beta
Classifier: Intended Audience :: Developers
Classifier: Programming Language :: Python :: 3
Classifier: Programming Language :: Python :: 3.10
Classifier: Programming Language :: Python :: 3.11
Classifier: Programming Language :: Python :: 3.12
Classifier: Programming Language :: Python :: 3.13
Classifier: Topic :: Scientific/Engineering :: Artificial Intelligence
Requires-Python: <3.14,>=3.10
License-File: LICENSE
Requires-Dist: pydantic>=2.11.3
Requires-Dist: pydantic-ai>=0.0.14
Requires-Dist: openai>=1.82.0
Requires-Dist: httpx>=0.28.1
Requires-Dist: python-dotenv>=1.0.1
Requires-Dist: aiofiles>=24.1.0
Requires-Dist: logfire>=3.21.1
Requires-Dist: redis>=6.2.0
Requires-Dist: beautifulsoup4>=4.12.0
Requires-Dist: numpy>=1.24.0
Requires-Dist: typing-extensions>=4.0.0
Requires-Dist: defusedxml>=0.7.1
Provides-Extra: anthropic
Requires-Dist: anthropic>=0.50.0; extra == "anthropic"
Provides-Extra: gemini
Requires-Dist: google-generativeai>=0.8.5; extra == "gemini"
Provides-Extra: redis
Requires-Dist: redis>=5.0.0; extra == "redis"
Provides-Extra: dev
Requires-Dist: pytest>=8.0.2; extra == "dev"
Requires-Dist: pytest-cov>=4.1.0; extra == "dev"
Requires-Dist: pytest-asyncio>=0.21.0; extra == "dev"
Requires-Dist: pytest-mock>=3.14.0; extra == "dev"
Requires-Dist: pytest-xdist>=3.6.1; extra == "dev"
Requires-Dist: black>=24.2.0; extra == "dev"
Requires-Dist: mypy>=1.9.0; extra == "dev"
Requires-Dist: ruff>=0.3.0; extra == "dev"
Requires-Dist: types-redis>=4.6.0; extra == "dev"
Requires-Dist: types-aiofiles>=24.1.0; extra == "dev"
Requires-Dist: ipython>=8.0.0; extra == "dev"
Requires-Dist: rich>=13.7.1; extra == "dev"
Requires-Dist: ipdb>=0.13.13; extra == "dev"
Requires-Dist: mkdocs>=1.6.0; extra == "dev"
Requires-Dist: mkdocs-material>=9.5.0; extra == "dev"
Requires-Dist: mkdocstrings[python]>=0.25.0; extra == "dev"
Requires-Dist: pre-commit>=3.7.1; extra == "dev"
Requires-Dist: watchdog>=4.0.1; extra == "dev"
Requires-Dist: python-dotenv>=1.0.1; extra == "dev"
Requires-Dist: psutil>=5.9.0; extra == "dev"
Requires-Dist: setuptools>=60.0.0; extra == "dev"
Requires-Dist: twine>=4.0.0; extra == "dev"
Provides-Extra: all
Requires-Dist: sifaka[anthropic,dev,gemini,redis]; extra == "all"
Dynamic: license-file
